prestapyt/__init__.py
prestapyt/dict2xml.py
prestapyt/prestapyt.py
prestapyt/version.py
prestapyt/xml2dict.py
prestapyt-0.11.1.dist-info/LICENSE
prestapyt-0.11.1.dist-info/METADATA
prestapyt-0.11.1.dist-info/WHEEL
prestapyt-0.11.1.dist-info/top_level.txt
prestapyt-0.11.1.dist-info/RECORD
